rtl/defines.v
parameter WIDTH = 32;

rtl/InstrMem.v
`include "defines.v"
module InstrMem (
	input wire 		clk,
	input wire 		rst_n,
	
	// Read address channel
	input wire 		arvalid,
	input wire [WIDTH-1:0] 	araddr,
	input wire [1:0] 	arburst, // arburst = 00
	input wire [2:0]	arsize, // arsize = 2 -> 2^2, a transaction is 4 byte
	input wire [7:0]	arlen, // the number of transaction
	output reg 		arready,	

	// Read data channel
	input wire 		rready,
	output reg 		rvalid,
	output reg [WIDTH-1:0] rdata,
	output reg 		rlast,
	output reg [1:0]	rresp
);
	
	reg [31:0] rom [0:100];

	initial begin
		$readmemh("test_file/test_program.mem", rom);
	end		

	always @(posedge clk or negedge rst_n) begin
		if (!rst_n) begin
			arready = 1'b1;
			rvalid = 1'b0;
			rdata = 32'dx;
			rlast = 1'b0;
			rresp = 2'd3;
		end
		else begin
			if (rvalid & rready) begin // data is valid and slave is ready to get data -> Complete to tranfer data to slave so it's ready to get araddr
				arready = 1'b1;
				rvalid = 1'b0;	
			end
			else if (rvalid & !rready) begin // data is valid but slave isn't ready to get data -> Not complete tranfering data so it's no ready to get araddr
				arready = 1'b0;
			end

			if (arvalid & arready) begin // it's ready to receive araddr and araddr is valid -> Execute receiving address
				rvalid = 1'b1;
				rdata = rom[araddr];
				rresp = 2'd0;
				rlast = 1'b1;
			end
		end
	end

endmodule

tb/tb_InstrMem.sv
`timescale 1ns/1ps

`include "../rtl/InstrMem.v"


module tb_InstrMem;

	// Input signals
	logic 			clk;
	logic 			rst_n;
	logic 			arvalid;
	logic [WIDTH-1:0]	araddr;
	logic [1:0] 		arburst;
	logic [2:0] 		arsize;
	logic [7:0]		arlen;
	logic 			rready;
	// Output signals
	logic 			arready;
	logic 			rvalid;
	logic [WIDTH-1:0]	rdata;
	logic 			rlast;
	logic 			rresp;

	initial begin
		$dumpfile("wave_file/tb_InstrMem.vcd");
		$dumpvars(0, tb_InstrMem);
	end

	always #(10) clk = ~clk;

	initial begin
		clk = 1'b0;
		rst_n = 1'b0;
		#(30)
		rst_n = 1'b1;
		#(20)
		araddr = 32'd0;
		arvalid = 1'b1;
		rready = 1'b0;
		#(20)
		araddr = 32'd1;
		arvalid = 1'b1;
		rready = 1'b1;
		#(1000)
		$finish;
	end


	InstrMem InstrMem_instance(clk, rst_n, arvalid, araddr, arburst, arsize, arlen, arready, rready, rvalid, rdata, rlast, rresp);
endmodule

wave_file/tb_InstrMem.vcd
$date
	Mon Dec 11 22:50:04 2023
$end
$version
	Questa Intel Starter FPGA Edition Version 2021.2
$end
$timescale
	1ps
$end

$scope module tb_InstrMem $end
$var reg 1 ! clk $end
$var reg 1 " rst_n $end
$var reg 1 # arvalid $end
$var reg 32 $ araddr [31:0] $end
$var reg 2 % arburst [1:0] $end
$var reg 3 & arsize [2:0] $end
$var reg 8 ' arlen [7:0] $end
$var reg 1 ( rready $end
$var reg 1 ) arready $end
$var reg 1 * rvalid $end
$var reg 32 + rdata [31:0] $end
$var reg 1 , rlast $end
$var reg 1 - rresp $end

$scope module InstrMem_instance $end
$var wire 1 . clk $end
$var wire 1 / rst_n $end
$var wire 1 0 arvalid $end
$var wire 1 1 araddr [31] $end
$var wire 1 2 araddr [30] $end
$var wire 1 3 araddr [29] $end
$var wire 1 4 araddr [28] $end
$var wire 1 5 araddr [27] $end
$var wire 1 6 araddr [26] $end
$var wire 1 7 araddr [25] $end
$var wire 1 8 araddr [24] $end
$var wire 1 9 araddr [23] $end
$var wire 1 : araddr [22] $end
$var wire 1 ; araddr [21] $end
$var wire 1 < araddr [20] $end
$var wire 1 = araddr [19] $end
$var wire 1 > araddr [18] $end
$var wire 1 ? araddr [17] $end
$var wire 1 @ araddr [16] $end
$var wire 1 A araddr [15] $end
$var wire 1 B araddr [14] $end
$var wire 1 C araddr [13] $end
$var wire 1 D araddr [12] $end
$var wire 1 E araddr [11] $end
$var wire 1 F araddr [10] $end
$var wire 1 G araddr [9] $end
$var wire 1 H araddr [8] $end
$var wire 1 I araddr [7] $end
$var wire 1 J araddr [6] $end
$var wire 1 K araddr [5] $end
$var wire 1 L araddr [4] $end
$var wire 1 M araddr [3] $end
$var wire 1 N araddr [2] $end
$var wire 1 O araddr [1] $end
$var wire 1 P araddr [0] $end
$var wire 1 Q arburst [1] $end
$var wire 1 R arburst [0] $end
$var wire 1 S arsize [2] $end
$var wire 1 T arsize [1] $end
$var wire 1 U arsize [0] $end
$var wire 1 V arlen [7] $end
$var wire 1 W arlen [6] $end
$var wire 1 X arlen [5] $end
$var wire 1 Y arlen [4] $end
$var wire 1 Z arlen [3] $end
$var wire 1 [ arlen [2] $end
$var wire 1 \ arlen [1] $end
$var wire 1 ] arlen [0] $end
$var reg 1 ^ arready $end
$var wire 1 _ rready $end
$var reg 1 ` rvalid $end
$var reg 32 a rdata [31:0] $end
$var reg 1 b rlast $end
$var reg 2 c rresp [1:0] $end
$upscope $end
$upscope $end
$enddefinitions $end
#0
$dumpvars
0!
0"
x#
bx $
bx %
bx &
bx '
x(
1)
0*
bx +
0,
1-
1^
0`
bx a
0b
b11 c
x_
x]
x\
x[
xZ
xY
xX
xW
xV
xU
xT
xS
xR
xQ
xP
xO
xN
xM
xL
xK
xJ
xI
xH
xG
xF
xE
xD
xC
xB
xA
x@
x?
x>
x=
x<
x;
x:
x9
x8
x7
x6
x5
x4
x3
x2
x1
x0
0/
0.
$end
#10000
1!
1.
#20000
0!
0.
#30000
1"
1!
1/
1.
#40000
0!
0.
#50000
b0 $
1#
0(
1!
0P
0O
0N
0M
0L
0K
0J
0I
0H
0G
0F
0E
0D
0C
0B
0A
0@
0?
0>
0=
0<
0;
0:
09
08
07
06
05
04
03
02
01
10
0_
1.
1`
b10100000010110111 a
b0 c
1b
1,
0-
b10100000010110111 +
1*
#60000
0!
0.
#70000
b1 $
1(
1!
1P
1_
1.
0`
1`
b11110000100110111 a
b11110000100110111 +
#80000
0!
0.
#90000
1!
1.
0`
1`
#100000
0!
0.
#110000
1!
1.
0`
1`
#120000
0!
0.
#130000
1!
1.
0`
1`
#140000
0!
0.
#150000
1!
1.
0`
1`
#160000
0!
0.
#170000
1!
1.
0`
1`
#180000
0!
0.
#190000
1!
1.
0`
1`
#200000
0!
0.
#210000
1!
1.
0`
1`
#220000
0!
0.
#230000
1!
1.
0`
1`
#240000
0!
0.
#250000
1!
1.
0`
1`
#260000
0!
0.
#270000
1!
1.
0`
1`
#280000
0!
0.
#290000
1!
1.
0`
1`
#300000
0!
0.
#310000
1!
1.
0`
1`
#320000
0!
0.
#330000
1!
1.
0`
1`
#340000
0!
0.
#350000
1!
1.
0`
1`
#360000
0!
0.
#370000
1!
1.
0`
1`
#380000
0!
0.
#390000
1!
1.
0`
1`
#400000
0!
0.
#410000
1!
1.
0`
1`
#420000
0!
0.
#430000
1!
1.
0`
1`
#440000
0!
0.
#450000
1!
1.
0`
1`
#460000
0!
0.
#470000
1!
1.
0`
1`
#480000
0!
0.
#490000
1!
1.
0`
1`
#500000
0!
0.
#510000
1!
1.
0`
1`
#520000
0!
0.
#530000
1!
1.
0`
1`
#540000
0!
0.
#550000
1!
1.
0`
1`
#560000
0!
0.
#570000
1!
1.
0`
1`
#580000
0!
0.
#590000
1!
1.
0`
1`
#600000
0!
0.
#610000
1!
1.
0`
1`
#620000
0!
0.
#630000
1!
1.
0`
1`
#640000
0!
0.
#650000
1!
1.
0`
1`
#660000
0!
0.
#670000
1!
1.
0`
1`
#680000
0!
0.
#690000
1!
1.
0`
1`
#700000
0!
0.
#710000
1!
1.
0`
1`
#720000
0!
0.
#730000
1!
1.
0`
1`
#740000
0!
0.
#750000
1!
1.
0`
1`
#760000
0!
0.
#770000
1!
1.
0`
1`
#780000
0!
0.
#790000
1!
1.
0`
1`
#800000
0!
0.
#810000
1!
1.
0`
1`
#820000
0!
0.
#830000
1!
1.
0`
1`
#840000
0!
0.
#850000
1!
1.
0`
1`
#860000
0!
0.
#870000
1!
1.
0`
1`
#880000
0!
0.
#890000
1!
1.
0`
1`
#900000
0!
0.
#910000
1!
1.
0`
1`
#920000
0!
0.
#930000
1!
1.
0`
1`
#940000
0!
0.
#950000
1!
1.
0`
1`
#960000
0!
0.
#970000
1!
1.
0`
1`
#980000
0!
0.
#990000
1!
1.
0`
1`
#1000000
0!
0.
#1010000
1!
1.
0`
1`
#1020000
0!
0.
#1030000
1!
1.
0`
1`
#1040000
0!
0.
#1050000
1!
1.
0`
1`
