rtl/PC_Control.v

module PC_Control(
	// Input signals
	input wire 			clk,
	input wire 			rst_n,
	input wire   		jal,
	input wire 			jalr_jcond,
	input wire [31:0]	jal_addr,
	input wire [31:0] 	jalr_jcond_addr,
	input wire 			rlast,
	// Output signal	
	output reg	[31:0]	pc_addr
);
	wire [31:0] next_pc = jal ? jal_addr : jalr_jcond ? jalr_jcond_addr : pc_addr + 32'd4;

	always @(posedge clk or negedge rst_n) begin
		if(!rst_n) begin
			pc_addr <= 32'd0;
		end
		else if (!rlast) begin
			pc_addr <= pc_addr;
		end
		else pc_addr <= next_pc;
	end

endmodule: PC_Control

tb/PC_Control.sv
`timescale 1ns/1ps

`include "../rtl/PC_Control.v"

module tb_PC_Control;

	logic 			clk;
	logic 			rst_n;
	logic   		jal;
	logic 			jalr_jcond;
	logic [31:0]	jal_addr;
	logic [31:0] 	jalr_jcond_addr;
	logic 			rlast;


	logic	[31:0]	pc_addr;
	


	initial begin
		$dumpfile("wave_file/tb_PC_Control.vcd");
		$dumpvars(0, tb_PC_Control);
	end

	always #(10) clk = ~clk;
	
	initial begin
		clk = 1'b0;
		rst_n = 1'b0;
		#(20)
		rst_n = 1'b1;
		rlast = 1'b1;
		jal = 1'b0;
		jalr_jcond = 1'b0;
		#(60)
		jal = 1'b1;
		jal_addr = 32'd10;
		#(40)
		jalr_jcond = 1'b1;
		jal = 1'b0;
		jalr_jcond_addr = 32'd20;
		#(40)
		rlast = 1'b0;
		#(100)
		$finish;
	end


	PC_Control PC_Control_instance(clk,rst_n,jal,jalr_jcond,jal_addr,jalr_jcond_addr,rlast,pc_addr);
endmodule

wave_file/tb_PC_Control.vcd
$date
	Thu Jan  4 18:23:21 2024
$end
$version
	Questa Intel Starter FPGA Edition Version 2021.2
$end
$timescale
	1ps
$end

$scope module tb_PC_Control $end
$var reg 1 ! clk $end
$var reg 1 " rst_n $end
$var reg 1 # jal $end
$var reg 1 $ jalr_jcond $end
$var reg 32 % jal_addr [31:0] $end
$var reg 32 & jalr_jcond_addr [31:0] $end
$var reg 1 ' rlast $end
$var reg 32 ( pc_addr [31:0] $end

$scope module PC_Control_instance $end
$var wire 1 ) clk $end
$var wire 1 * rst_n $end
$var wire 1 + jal $end
$var wire 1 , jalr_jcond $end
$var wire 1 - jal_addr [31] $end
$var wire 1 . jal_addr [30] $end
$var wire 1 / jal_addr [29] $end
$var wire 1 0 jal_addr [28] $end
$var wire 1 1 jal_addr [27] $end
$var wire 1 2 jal_addr [26] $end
$var wire 1 3 jal_addr [25] $end
$var wire 1 4 jal_addr [24] $end
$var wire 1 5 jal_addr [23] $end
$var wire 1 6 jal_addr [22] $end
$var wire 1 7 jal_addr [21] $end
$var wire 1 8 jal_addr [20] $end
$var wire 1 9 jal_addr [19] $end
$var wire 1 : jal_addr [18] $end
$var wire 1 ; jal_addr [17] $end
$var wire 1 < jal_addr [16] $end
$var wire 1 = jal_addr [15] $end
$var wire 1 > jal_addr [14] $end
$var wire 1 ? jal_addr [13] $end
$var wire 1 @ jal_addr [12] $end
$var wire 1 A jal_addr [11] $end
$var wire 1 B jal_addr [10] $end
$var wire 1 C jal_addr [9] $end
$var wire 1 D jal_addr [8] $end
$var wire 1 E jal_addr [7] $end
$var wire 1 F jal_addr [6] $end
$var wire 1 G jal_addr [5] $end
$var wire 1 H jal_addr [4] $end
$var wire 1 I jal_addr [3] $end
$var wire 1 J jal_addr [2] $end
$var wire 1 K jal_addr [1] $end
$var wire 1 L jal_addr [0] $end
$var wire 1 M jalr_jcond_addr [31] $end
$var wire 1 N jalr_jcond_addr [30] $end
$var wire 1 O jalr_jcond_addr [29] $end
$var wire 1 P jalr_jcond_addr [28] $end
$var wire 1 Q jalr_jcond_addr [27] $end
$var wire 1 R jalr_jcond_addr [26] $end
$var wire 1 S jalr_jcond_addr [25] $end
$var wire 1 T jalr_jcond_addr [24] $end
$var wire 1 U jalr_jcond_addr [23] $end
$var wire 1 V jalr_jcond_addr [22] $end
$var wire 1 W jalr_jcond_addr [21] $end
$var wire 1 X jalr_jcond_addr [20] $end
$var wire 1 Y jalr_jcond_addr [19] $end
$var wire 1 Z jalr_jcond_addr [18] $end
$var wire 1 [ jalr_jcond_addr [17] $end
$var wire 1 \ jalr_jcond_addr [16] $end
$var wire 1 ] jalr_jcond_addr [15] $end
$var wire 1 ^ jalr_jcond_addr [14] $end
$var wire 1 _ jalr_jcond_addr [13] $end
$var wire 1 ` jalr_jcond_addr [12] $end
$var wire 1 a jalr_jcond_addr [11] $end
$var wire 1 b jalr_jcond_addr [10] $end
$var wire 1 c jalr_jcond_addr [9] $end
$var wire 1 d jalr_jcond_addr [8] $end
$var wire 1 e jalr_jcond_addr [7] $end
$var wire 1 f jalr_jcond_addr [6] $end
$var wire 1 g jalr_jcond_addr [5] $end
$var wire 1 h jalr_jcond_addr [4] $end
$var wire 1 i jalr_jcond_addr [3] $end
$var wire 1 j jalr_jcond_addr [2] $end
$var wire 1 k jalr_jcond_addr [1] $end
$var wire 1 l jalr_jcond_addr [0] $end
$var wire 1 m rlast $end
$var reg 32 n pc_addr [31:0] $end
$var wire 1 o next_pc [31] $end
$var wire 1 p next_pc [30] $end
$var wire 1 q next_pc [29] $end
$var wire 1 r next_pc [28] $end
$var wire 1 s next_pc [27] $end
$var wire 1 t next_pc [26] $end
$var wire 1 u next_pc [25] $end
$var wire 1 v next_pc [24] $end
$var wire 1 w next_pc [23] $end
$var wire 1 x next_pc [22] $end
$var wire 1 y next_pc [21] $end
$var wire 1 z next_pc [20] $end
$var wire 1 { next_pc [19] $end
$var wire 1 | next_pc [18] $end
$var wire 1 } next_pc [17] $end
$var wire 1 ~ next_pc [16] $end
$var wire 1 !! next_pc [15] $end
$var wire 1 "! next_pc [14] $end
$var wire 1 #! next_pc [13] $end
$var wire 1 $! next_pc [12] $end
$var wire 1 %! next_pc [11] $end
$var wire 1 &! next_pc [10] $end
$var wire 1 '! next_pc [9] $end
$var wire 1 (! next_pc [8] $end
$var wire 1 )! next_pc [7] $end
$var wire 1 *! next_pc [6] $end
$var wire 1 +! next_pc [5] $end
$var wire 1 ,! next_pc [4] $end
$var wire 1 -! next_pc [3] $end
$var wire 1 .! next_pc [2] $end
$var wire 1 /! next_pc [1] $end
$var wire 1 0! next_pc [0] $end
$upscope $end
$upscope $end
$enddefinitions $end
#0
$dumpvars
0!
0"
x#
x$
bx %
bx &
x'
b0 (
b0 n
x0!
x/!
x.!
x-!
x,!
x+!
x*!
x)!
x(!
x'!
x&!
x%!
x$!
x#!
x"!
x!!
x~
x}
x|
x{
xz
xy
xx
xw
xv
xu
xt
xs
xr
xq
xp
xo
xm
xl
xk
xj
xi
xh
xg
xf
xe
xd
xc
xb
xa
x`
x_
x^
x]
x\
x[
xZ
xY
xX
xW
xV
xU
xT
xS
xR
xQ
xP
xO
xN
xM
xL
xK
xJ
xI
xH
xG
xF
xE
xD
xC
xB
xA
x@
x?
x>
x=
x<
x;
x:
x9
x8
x7
x6
x5
x4
x3
x2
x1
x0
x/
x.
x-
x,
x+
0*
0)
$end
#10000
1!
1)
#20000
1"
1'
0#
0$
0!
1m
0+
0,
00!
0/!
1.!
0-!
0,!
0+!
0*!
0)!
0(!
0'!
0&!
0%!
0$!
0#!
0"!
0!!
0~
0}
0|
0{
0z
0y
0x
0w
0v
0u
0t
0s
0r
0q
0p
0o
1*
0)
#30000
1!
1)
b100 n
b100 (
0.!
1-!
#40000
0!
0)
#50000
1!
1)
b1000 n
b1000 (
1.!
#60000
0!
0)
#70000
1!
1)
b1100 n
b1100 (
0.!
0-!
1,!
#80000
1#
b1010 %
0!
1+
0L
1K
0J
1I
0H
0G
0F
0E
0D
0C
0B
0A
0@
0?
0>
0=
0<
0;
0:
09
08
07
06
05
04
03
02
01
00
0/
0.
0-
1/!
1-!
0,!
0)
#90000
1!
1)
b1010 n
b1010 (
#100000
0!
0)
#110000
1!
1)
#120000
1$
0#
b10100 &
0!
1,
0+
0l
0k
1j
0i
1h
0g
0f
0e
0d
0c
0b
0a
0`
0_
0^
0]
0\
0[
0Z
0Y
0X
0W
0V
0U
0T
0S
0R
0Q
0P
0O
0N
0M
0/!
1.!
0-!
1,!
0)
#130000
1!
1)
b10100 n
b10100 (
#140000
0!
0)
#150000
1!
1)
#160000
0'
0!
0m
0)
